{
  "name": "pose_gsr_ecg",
  "config": {
    "n_seeds": 3,
    "feature_selection": "none",
    "use_pca": false,
    "pca_variance": 0.95,
    "write_cm": true,
    "tune_hyperparameters": false,
    "tune_n_iter": 30,
    "tune_cv_folds": 5,
    "use_pose_derivatives": false,
    "use_time_features": false,
    "class_config": "all",
    "include_order": false,
    "name": "pose_gsr_ecg",
    "feature_groups": [
      "pose",
      "gsr",
      "ecg"
    ],
    "split_strategy": "lopo"
  },
  "metrics": {
    "test_acc_mean": 0.34862775162839355,
    "test_acc_std": 0.12618551765698094,
    "test_bal_acc_mean": 0.34575580365054054,
    "test_bal_acc_std": 0.12618512595810757,
    "test_f1_mean": 0.27186716880149664,
    "test_f1_std": 0.12706655261602018,
    "test_kappa_mean": 0.028762007240756608,
    "test_kappa_std": 0.176995931896552
  },
  "participant_results": [
    {
      "participant": "3208",
      "n_seeds": 3,
      "test_acc_mean": 0.35555555555555557,
      "test_acc_std": 0.022222222222222227,
      "test_bal_acc_mean": 0.35555555555555557,
      "test_bal_acc_std": 0.022222222222222227,
      "test_f1_mean": 0.23553551386884722,
      "test_f1_std": 0.017897806904885637,
      "test_kappa_mean": 0.03333333333333336,
      "test_kappa_std": 0.033333333333333326
    },
    {
      "participant": "3209",
      "n_seeds": 3,
      "test_acc_mean": 0.3037037037037037,
      "test_acc_std": 0.012830005981991702,
      "test_bal_acc_mean": 0.30370370370370375,
      "test_bal_acc_std": 0.01283000598199167,
      "test_f1_mean": 0.15705280475036543,
      "test_f1_std": 0.00454476966138148,
      "test_kappa_mean": -0.04444444444444443,
      "test_kappa_std": 0.01924500897298752
    },
    {
      "participant": "3210",
      "n_seeds": 3,
      "test_acc_mean": 0.3333333333333333,
      "test_acc_std": 0.0,
      "test_bal_acc_mean": 0.3333333333333333,
      "test_bal_acc_std": 0.0,
      "test_f1_mean": 0.16666666666666666,
      "test_f1_std": 0.0,
      "test_kappa_mean": 0.0,
      "test_kappa_std": 0.0
    },
    {
      "participant": "3214",
      "n_seeds": 3,
      "test_acc_mean": 0.6814814814814815,
      "test_acc_std": 0.04625924443258069,
      "test_bal_acc_mean": 0.6814814814814815,
      "test_bal_acc_std": 0.04625924443258075,
      "test_f1_mean": 0.6175885782412117,
      "test_f1_std": 0.08602672164285505,
      "test_kappa_mean": 0.5222222222222223,
      "test_kappa_std": 0.06938886664887108
    },
    {
      "participant": "3215",
      "n_seeds": 3,
      "test_acc_mean": 0.31851851851851853,
      "test_acc_std": 0.07143445008142932,
      "test_bal_acc_mean": 0.3185185185185185,
      "test_bal_acc_std": 0.07143445008142928,
      "test_f1_mean": 0.29949485358288697,
      "test_f1_std": 0.06566734590226427,
      "test_kappa_mean": -0.022222222222222254,
      "test_kappa_std": 0.10715167512214396
    },
    {
      "participant": "3216",
      "n_seeds": 3,
      "test_acc_mean": 0.2740740740740741,
      "test_acc_std": 0.03394500514782105,
      "test_bal_acc_mean": 0.2740740740740741,
      "test_bal_acc_std": 0.03394500514782105,
      "test_f1_mean": 0.16377500495147554,
      "test_f1_std": 0.029103780888697334,
      "test_kappa_mean": -0.08888888888888886,
      "test_kappa_std": 0.050917507721731474
    },
    {
      "participant": "3217",
      "n_seeds": 3,
      "test_acc_mean": 0.3481481481481481,
      "test_acc_std": 0.025660011963983372,
      "test_bal_acc_mean": 0.3481481481481481,
      "test_bal_acc_std": 0.025660011963983372,
      "test_f1_mean": 0.2037037037037037,
      "test_f1_std": 0.06415002990995844,
      "test_kappa_mean": 0.02222222222222218,
      "test_kappa_std": 0.03849001794597497
    },
    {
      "participant": "3218",
      "n_seeds": 3,
      "test_acc_mean": 0.4444444444444444,
      "test_acc_std": 0.03849001794597504,
      "test_bal_acc_mean": 0.4444444444444445,
      "test_bal_acc_std": 0.03849001794597508,
      "test_f1_mean": 0.3879789084244514,
      "test_f1_std": 0.011505219897579709,
      "test_kappa_mean": 0.16666666666666663,
      "test_kappa_std": 0.05773502691896256
    },
    {
      "participant": "3219",
      "n_seeds": 3,
      "test_acc_mean": 0.4583333333333333,
      "test_acc_std": 0.0520416499866533,
      "test_bal_acc_mean": 0.41111111111111115,
      "test_bal_acc_std": 0.05091750772173154,
      "test_f1_mean": 0.3630943068716848,
      "test_f1_std": 0.07684543664790462,
      "test_kappa_mean": 0.14913924677977122,
      "test_kappa_std": 0.07792623394461054
    },
    {
      "participant": "3220",
      "n_seeds": 3,
      "test_acc_mean": 0.2962962962962963,
      "test_acc_std": 0.033945005147821034,
      "test_bal_acc_mean": 0.2962962962962963,
      "test_bal_acc_std": 0.03394500514782103,
      "test_f1_mean": 0.19833116182445387,
      "test_f1_std": 0.02353358425019803,
      "test_kappa_mean": -0.05555555555555566,
      "test_kappa_std": 0.05091750772173161
    },
    {
      "participant": "3221",
      "n_seeds": 3,
      "test_acc_mean": 0.28888888888888886,
      "test_acc_std": 0.04444444444444444,
      "test_bal_acc_mean": 0.2888888888888889,
      "test_bal_acc_std": 0.044444444444444425,
      "test_f1_mean": 0.25947418683050866,
      "test_f1_std": 0.03576443016861822,
      "test_kappa_mean": -0.06666666666666654,
      "test_kappa_std": 0.06666666666666671
    },
    {
      "participant": "3223",
      "n_seeds": 3,
      "test_acc_mean": 0.07407407407407407,
      "test_acc_std": 0.02566001196398337,
      "test_bal_acc_mean": 0.07407407407407407,
      "test_bal_acc_std": 0.02566001196398337,
      "test_f1_mean": 0.06873638344226579,
      "test_f1_std": 0.02117973158678227,
      "test_kappa_mean": -0.3888888888888889,
      "test_kappa_std": 0.03849001794597504
    },
    {
      "participant": "3224",
      "n_seeds": 3,
      "test_acc_mean": 0.4740740740740741,
      "test_acc_std": 0.025660011963983372,
      "test_bal_acc_mean": 0.4740740740740741,
      "test_bal_acc_std": 0.025660011963983403,
      "test_f1_mean": 0.3737467161440524,
      "test_f1_std": 0.029057160909421946,
      "test_kappa_mean": 0.21111111111111105,
      "test_kappa_std": 0.03849001794597504
    },
    {
      "participant": "3225",
      "n_seeds": 3,
      "test_acc_mean": 0.28888888888888886,
      "test_acc_std": 0.06666666666666668,
      "test_bal_acc_mean": 0.2888888888888889,
      "test_bal_acc_std": 0.06666666666666668,
      "test_f1_mean": 0.2379620267385687,
      "test_f1_std": 0.05666858863097706,
      "test_kappa_mean": -0.06666666666666661,
      "test_kappa_std": 0.10000000000000003
    },
    {
      "participant": "3226",
      "n_seeds": 3,
      "test_acc_mean": 0.5703703703703703,
      "test_acc_std": 0.03394500514782103,
      "test_bal_acc_mean": 0.5703703703703704,
      "test_bal_acc_std": 0.03394500514782104,
      "test_f1_mean": 0.4845095005935938,
      "test_f1_std": 0.027957197717537758,
      "test_kappa_mean": 0.35555555555555557,
      "test_kappa_std": 0.050917507721731495
    },
    {
      "participant": "3227",
      "n_seeds": 3,
      "test_acc_mean": 0.25925925925925924,
      "test_acc_std": 0.012830005981991686,
      "test_bal_acc_mean": 0.25925925925925924,
      "test_bal_acc_std": 0.012830005981991686,
      "test_f1_mean": 0.1380534670008354,
      "test_f1_std": 0.006276098246164051,
      "test_kappa_mean": -0.11111111111111116,
      "test_kappa_std": 0.01924500897298746
    },
    {
      "participant": "3228",
      "n_seeds": 3,
      "test_acc_mean": 0.22222222222222224,
      "test_acc_std": 0.07349309197401642,
      "test_bal_acc_mean": 0.18888888888888888,
      "test_bal_acc_std": 0.07777777777777778,
      "test_f1_mean": 0.19624773315402325,
      "test_f1_std": 0.09090973593436781,
      "test_kappa_mean": -0.3286647992530343,
      "test_kappa_std": 0.13393730557436437
    },
    {
      "participant": "3229",
      "n_seeds": 3,
      "test_acc_mean": 0.2518518518518518,
      "test_acc_std": 0.051320023927966744,
      "test_bal_acc_mean": 0.2518518518518518,
      "test_bal_acc_std": 0.05132002392796674,
      "test_f1_mean": 0.26515845210542105,
      "test_f1_std": 0.05419502377095197,
      "test_kappa_mean": -0.1222222222222223,
      "test_kappa_std": 0.07698003589195009
    },
    {
      "participant": "3230",
      "n_seeds": 3,
      "test_acc_mean": 0.47407407407407404,
      "test_acc_std": 0.01283000598199167,
      "test_bal_acc_mean": 0.47407407407407404,
      "test_bal_acc_std": 0.012830005981991702,
      "test_f1_mean": 0.393620444810921,
      "test_f1_std": 0.03313593034738791,
      "test_kappa_mean": 0.2111111111111111,
      "test_kappa_std": 0.019245008972987584
    },
    {
      "participant": "3232",
      "n_seeds": 3,
      "test_acc_mean": 0.43703703703703706,
      "test_acc_std": 0.04625924443258071,
      "test_bal_acc_mean": 0.43703703703703706,
      "test_bal_acc_std": 0.04625924443258073,
      "test_f1_mean": 0.3849468635080959,
      "test_f1_std": 0.06392873125587833,
      "test_kappa_mean": 0.15555555555555556,
      "test_kappa_std": 0.06938886664887103
    },
    {
      "participant": "3233",
      "n_seeds": 3,
      "test_acc_mean": 0.2962962962962963,
      "test_acc_std": 0.012830005981991702,
      "test_bal_acc_mean": 0.29629629629629634,
      "test_bal_acc_std": 0.01283000598199167,
      "test_f1_mean": 0.1893830012787784,
      "test_f1_std": 0.01154737743701047,
      "test_kappa_mean": -0.05555555555555558,
      "test_kappa_std": 0.01924500897298746
    },
    {
      "participant": "3234",
      "n_seeds": 3,
      "test_acc_mean": 0.43703703703703706,
      "test_acc_std": 0.078041879650761,
      "test_bal_acc_mean": 0.43703703703703706,
      "test_bal_acc_std": 0.078041879650761,
      "test_f1_mean": 0.3826094620990119,
      "test_f1_std": 0.06865825282635174,
      "test_kappa_mean": 0.15555555555555556,
      "test_kappa_std": 0.11706281947614157
    },
    {
      "participant": "3235",
      "n_seeds": 3,
      "test_acc_mean": 0.3703703703703704,
      "test_acc_std": 0.01283000598199167,
      "test_bal_acc_mean": 0.3703703703703704,
      "test_bal_acc_std": 0.01283000598199167,
      "test_f1_mean": 0.24294117647058824,
      "test_f1_std": 0.01654989207707489,
      "test_kappa_mean": 0.055555555555555546,
      "test_kappa_std": 0.01924500897298752
    },
    {
      "participant": "3236",
      "n_seeds": 3,
      "test_acc_mean": 0.40740740740740744,
      "test_acc_std": 0.05592469952052407,
      "test_bal_acc_mean": 0.4074074074074074,
      "test_bal_acc_std": 0.05592469952052404,
      "test_f1_mean": 0.3252637332235839,
      "test_f1_std": 0.08924735119659208,
      "test_kappa_mean": 0.11111111111111109,
      "test_kappa_std": 0.0838870492807861
    },
    {
      "participant": "3237",
      "n_seeds": 3,
      "test_acc_mean": 0.2888888888888889,
      "test_acc_std": 0.04444444444444444,
      "test_bal_acc_mean": 0.2888888888888889,
      "test_bal_acc_std": 0.04444444444444444,
      "test_f1_mean": 0.15162388079426437,
      "test_f1_std": 0.018082805338639558,
      "test_kappa_mean": -0.06666666666666672,
      "test_kappa_std": 0.06666666666666654
    },
    {
      "participant": "3238",
      "n_seeds": 3,
      "test_acc_mean": 0.48888888888888893,
      "test_acc_std": 0.03849001794597504,
      "test_bal_acc_mean": 0.4888888888888889,
      "test_bal_acc_std": 0.03849001794597508,
      "test_f1_mean": 0.48941965132997517,
      "test_f1_std": 0.041817321878380644,
      "test_kappa_mean": 0.2333333333333333,
      "test_kappa_std": 0.05773502691896263
    },
    {
      "participant": "3239",
      "n_seeds": 3,
      "test_acc_mean": 0.3821138211382114,
      "test_acc_std": 0.014081713882673812,
      "test_bal_acc_mean": 0.35353535353535354,
      "test_bal_acc_std": 0.017495462702715917,
      "test_f1_mean": 0.22936683912293668,
      "test_f1_std": 0.025816475451568646,
      "test_kappa_mean": 0.028037383177570097,
      "test_kappa_std": 0.024281086087414076
    },
    {
      "participant": "3240",
      "n_seeds": 3,
      "test_acc_mean": 0.30370370370370375,
      "test_acc_std": 0.10020555006273099,
      "test_bal_acc_mean": 0.3037037037037037,
      "test_bal_acc_std": 0.10020555006273095,
      "test_f1_mean": 0.23619954369579557,
      "test_f1_std": 0.07071302740881881,
      "test_kappa_mean": -0.04444444444444436,
      "test_kappa_std": 0.1503083250940965
    },
    {
      "participant": "3241",
      "n_seeds": 3,
      "test_acc_mean": 0.5185185185185185,
      "test_acc_std": 0.04625924443258073,
      "test_bal_acc_mean": 0.5185185185185185,
      "test_bal_acc_std": 0.04625924443258072,
      "test_f1_mean": 0.5186089323251662,
      "test_f1_std": 0.04019339055367049,
      "test_kappa_mean": 0.2777777777777778,
      "test_kappa_std": 0.06938886664887113
    },
    {
      "participant": "3242",
      "n_seeds": 3,
      "test_acc_mean": 0.22962962962962963,
      "test_acc_std": 0.04625924443258072,
      "test_bal_acc_mean": 0.22962962962962963,
      "test_bal_acc_std": 0.04625924443258072,
      "test_f1_mean": 0.20073387410946056,
      "test_f1_std": 0.03712309630315694,
      "test_kappa_mean": -0.15555555555555559,
      "test_kappa_std": 0.06938886664887109
    },
    {
      "participant": "3243",
      "n_seeds": 3,
      "test_acc_mean": 0.3333333333333333,
      "test_acc_std": 0.0,
      "test_bal_acc_mean": 0.3333333333333333,
      "test_bal_acc_std": 0.0,
      "test_f1_mean": 0.16666666666666666,
      "test_f1_std": 0.0,
      "test_kappa_mean": 0.0,
      "test_kappa_std": 0.0
    },
    {
      "participant": "3244",
      "n_seeds": 3,
      "test_acc_mean": 0.1851851851851852,
      "test_acc_std": 0.09251848886516144,
      "test_bal_acc_mean": 0.1851851851851852,
      "test_bal_acc_std": 0.09251848886516147,
      "test_f1_mean": 0.17657797204796022,
      "test_f1_std": 0.09292419535027116,
      "test_kappa_mean": -0.22222222222222224,
      "test_kappa_std": 0.138777733297742
    },
    {
      "participant": "3245",
      "n_seeds": 3,
      "test_acc_mean": 0.39999999999999997,
      "test_acc_std": 0.03849001794597504,
      "test_bal_acc_mean": 0.39999999999999997,
      "test_bal_acc_std": 0.03849001794597504,
      "test_f1_mean": 0.2999385975026921,
      "test_f1_std": 0.046388740328674606,
      "test_kappa_mean": 0.09999999999999998,
      "test_kappa_std": 0.05773502691896256
    },
    {
      "participant": "3246",
      "n_seeds": 3,
      "test_acc_mean": 0.28148148148148144,
      "test_acc_std": 0.025660011963983372,
      "test_bal_acc_mean": 0.28148148148148144,
      "test_bal_acc_std": 0.025660011963983372,
      "test_f1_mean": 0.2262701297789017,
      "test_f1_std": 0.0183048880244942,
      "test_kappa_mean": -0.07777777777777788,
      "test_kappa_std": 0.03849001794597504
    },
    {
      "participant": "3247",
      "n_seeds": 3,
      "test_acc_mean": 0.43703703703703706,
      "test_acc_std": 0.01283000598199167,
      "test_bal_acc_mean": 0.43703703703703706,
      "test_bal_acc_std": 0.012830005981991702,
      "test_f1_mean": 0.36202019927300144,
      "test_f1_std": 0.025635077391295735,
      "test_kappa_mean": 0.15555555555555553,
      "test_kappa_std": 0.01924500897298752
    },
    {
      "participant": "3248",
      "n_seeds": 3,
      "test_acc_mean": 0.4222222222222222,
      "test_acc_std": 0.03849001794597504,
      "test_bal_acc_mean": 0.4222222222222222,
      "test_bal_acc_std": 0.03849001794597506,
      "test_f1_mean": 0.3472945180993012,
      "test_f1_std": 0.04087822379147071,
      "test_kappa_mean": 0.13333333333333333,
      "test_kappa_std": 0.0577350269189625
    },
    {
      "participant": "3249",
      "n_seeds": 3,
      "test_acc_mean": 0.022222222222222223,
      "test_acc_std": 0.03849001794597505,
      "test_bal_acc_mean": 0.022222222222222223,
      "test_bal_acc_std": 0.03849001794597505,
      "test_f1_mean": 0.041666666666666664,
      "test_f1_std": 0.07216878364870323,
      "test_kappa_mean": 0.0,
      "test_kappa_std": 0.0
    },
    {
      "participant": "3250",
      "n_seeds": 3,
      "test_acc_mean": 0.28888888888888886,
      "test_acc_std": 0.05879447357921313,
      "test_bal_acc_mean": 0.28888888888888886,
      "test_bal_acc_std": 0.05879447357921313,
      "test_f1_mean": 0.14869029275808937,
      "test_f1_std": 0.024171099362177945,
      "test_kappa_mean": -0.06666666666666672,
      "test_kappa_std": 0.0881917103688197
    }
  ],
  "selected_features": [],
  "n_participants": 38,
  "n_seeds": 3,
  "n_features": 391,
  "timestamp": "2025-10-17T10:13:15.402892"
}